diffusion_curvature/__init__.py
diffusion_curvature/_modidx.py
diffusion_curvature/core.py
diffusion_curvature/datasets.py
diffusion_curvature/distances.py
diffusion_curvature/graphtools.py
diffusion_curvature/kernels.py
diffusion_curvature/manifold_graph.py
diffusion_curvature-0.0.3.dist-info/LICENSE
diffusion_curvature-0.0.3.dist-info/METADATA
diffusion_curvature-0.0.3.dist-info/SOURCES.sync-conflict-20230806-204323-NXPHTTX.txt
diffusion_curvature-0.0.3.dist-info/WHEEL
diffusion_curvature-0.0.3.dist-info/entry_points.txt
diffusion_curvature-0.0.3.dist-info/requires.sync-conflict-20230806-200642-NXPHTTX.txt
diffusion_curvature-0.0.3.dist-info/top_level.txt
diffusion_curvature-0.0.3.dist-info/RECORD
