Metadata-Version: 2.1
Name: diffusion-curvature
Version: 0.0.3
Summary: Fast, pointwise graph curvature
Home-page: https://github.com/professorwug/diffusion_curvature
Author: Kincaid
Author-email: dev@riddle.press
License: Apache Software License 2.0
Keywords: nbdev jupyter notebook python
Classifier: Development Status :: 4 - Beta
Classifier: Intended Audience :: Developers
Classifier: Natural Language :: English
Classifier: Programming Language :: Python :: 3.7
Classifier: Programming Language :: Python :: 3.8
Classifier: Programming Language :: Python :: 3.9
Classifier: Programming Language :: Python :: 3.10
Classifier: License :: OSI Approved :: Apache Software License
Requires-Python: >=3.7
License-File: LICENSE
Requires-Dist: numpy
Requires-Dist: pandas
Requires-Dist: scikit-learn
Requires-Dist: scipy
Requires-Dist: sympy
Requires-Dist: numba
Requires-Dist: tqdm
Requires-Dist: rich
Requires-Dist: typer
Requires-Dist: matplotlib
Requires-Dist: plotly
Requires-Dist: nbdev (>=2.3.12)
Requires-Dist: pyyaml
Requires-Dist: graphtools
Requires-Dist: scikit-dimension
Provides-Extra: dev
Requires-Dist: nbdev ; extra == 'dev'
